__init__.py
sysutil.py
sysutil_lib-0.6.0.dist-info/licenses/LICENSE
sysutil_lib-0.6.0.dist-info/METADATA
sysutil_lib-0.6.0.dist-info/WHEEL
sysutil_lib-0.6.0.dist-info/top_level.txt
sysutil_lib-0.6.0.dist-info/RECORD
