Metadata-Version: 2.4
Name: sysutil-lib
Version: 0.6.0
Summary: Linux system information library
Author: ryzeon-dev
Project-URL: Homepage, https://github.com/ryzeon-dev/sysutil
Classifier: Programming Language :: Python :: 3
Classifier: License :: OSI Approved :: GNU Affero General Public License v3 or later (AGPLv3+)
Requires-Python: >=3.8
License-File: LICENSE
Dynamic: license-file
